<?xml version="1.0" encoding="UTF-8" standalone="yes"?>
<w:fonts xmlns:mc="http://schemas.openxmlformats.org/markup-compatibility/2006" xmlns:r="http://schemas.openxmlformats.org/officeDocument/2006/relationships" xmlns:w="http://schemas.openxmlformats.org/wordprocessingml/2006/main" xmlns:w14="http://schemas.microsoft.com/office/word/2010/wordml" xmlns:w15="http://schemas.microsoft.com/office/word/2012/wordml" xmlns:w16cex="http://schemas.microsoft.com/office/word/2018/wordml/cex" xmlns:w16cid="http://schemas.microsoft.com/office/word/2016/wordml/cid" xmlns:w16="http://schemas.microsoft.com/office/word/2018/wordml" xmlns:w16se="http://schemas.microsoft.com/office/word/2015/wordml/symex" mc:Ignorable="w14 w15 w16se w16cid w16 w16cex"><w:font w:name="Calibri"><w:panose1 w:val="020F0502020204030204"/><w:charset w:val="00"/><w:family w:val="swiss"/><w:pitch w:val="variable"/><w:sig w:usb0="E00002FF" w:usb1="4000ACFF" w:usb2="00000001" w:usb3="00000000" w:csb0="0000019F" w:csb1="00000000"/><w:embedRegular r:id="rId1" w:fontKey="{AD9425A4-3454-45AC-84F1-50DFC92639D9}"/></w:font><w:font w:name="Times New Roman"><w:panose1 w:val="02020603050405020304"/><w:charset w:val="00"/><w:family w:val="roman"/><w:pitch w:val="variable"/><w:sig w:usb0="E0002AFF" w:usb1="C0007843" w:usb2="00000009" w:usb3="00000000" w:csb0="000001FF" w:csb1="00000000"/></w:font><w:font w:name="Tahoma"><w:panose1 w:val="020B0604030504040204"/><w:charset w:val="00"/><w:family w:val="swiss"/><w:pitch w:val="variable"/><w:sig w:usb0="E1002EFF" w:usb1="C000605B" w:usb2="00000029" w:usb3="00000000" w:csb0="000101FF" w:csb1="00000000"/><w:embedRegular r:id="rId2" w:subsetted="1" w:fontKey="{D3F637BF-574B-4FF3-8A92-5E6475D2392A}"/></w:font><w:font w:name="Microsoft Sans Serif"><w:panose1 w:val="020B0604020202020204"/><w:charset w:val="00"/><w:family w:val="swiss"/><w:pitch w:val="variable"/><w:sig w:usb0="E5002EFF" w:usb1="C000605B" w:usb2="00000029" w:usb3="00000000" w:csb0="000101FF" w:csb1="00000000"/><w:embedRegular r:id="rId3" w:subsetted="1" w:fontKey="{05783199-5553-49C6-ABB8-021AEB91C10A}"/></w:font><w:font w:name="Lucida Sans"><w:panose1 w:val="020B0602030504020204"/><w:charset w:val="00"/><w:family w:val="swiss"/><w:pitch w:val="variable"/><w:sig w:usb0="00000003" w:usb1="00000000" w:usb2="00000000" w:usb3="00000000" w:csb0="00000001" w:csb1="00000000"/><w:embedRegular r:id="rId4" w:subsetted="1" w:fontKey="{E7957D16-E877-496E-918A-E8274275C5EC}"/></w:font><w:font w:name="Bookman Old Style"><w:panose1 w:val="02050604050505020204"/><w:charset w:val="00"/><w:family w:val="roman"/><w:pitch w:val="variable"/><w:sig w:usb0="00000287" w:usb1="00000000" w:usb2="00000000" w:usb3="00000000" w:csb0="0000009F" w:csb1="00000000"/><w:embedRegular r:id="rId5" w:subsetted="1" w:fontKey="{1F8B83F1-22CD-4B2E-948E-2AD2AD70AB5F}"/></w:font><w:font w:name="Comic Sans MS"><w:panose1 w:val="030F0702030302020204"/><w:charset w:val="00"/><w:family w:val="script"/><w:pitch w:val="variable"/><w:sig w:usb0="00000287" w:usb1="00000013" w:usb2="00000000" w:usb3="00000000" w:csb0="0000009F" w:csb1="00000000"/><w:embedRegular r:id="rId6" w:subsetted="1" w:fontKey="{8FDDE8CB-219C-4BF5-B32B-75E62ADF359B}"/></w:font><w:font w:name="Cordia New"><w:panose1 w:val="020B0304020202020204"/><w:charset w:val="DE"/><w:family w:val="swiss"/><w:pitch w:val="variable"/><w:sig w:usb0="81000003" w:usb1="00000000" w:usb2="00000000" w:usb3="00000000" w:csb0="00010001" w:csb1="00000000"/><w:embedRegular r:id="rId7" w:subsetted="1" w:fontKey="{78652328-E913-4301-90DC-B598F1041726}"/></w:font><w:font w:name="Arial"><w:panose1 w:val="020B0604020202020204"/><w:charset w:val="00"/><w:family w:val="swiss"/><w:pitch w:val="variable"/><w:sig w:usb0="E0002AFF" w:usb1="C0007843" w:usb2="00000009" w:usb3="00000000" w:csb0="000001FF" w:csb1="00000000"/></w:font><w:font w:name="Corbel"><w:panose1 w:val="020B0503020204020204"/><w:charset w:val="00"/><w:family w:val="swiss"/><w:pitch w:val="variable"/><w:sig w:usb0="A00002EF" w:usb1="4000A44B" w:usb2="00000000" w:usb3="00000000" w:csb0="0000019F" w:csb1="00000000"/><w:embedRegular r:id="rId8" w:subsetted="1" w:fontKey="{D115602C-692C-42A0-A7BB-BD33AF1C5D73}"/></w:font><w:font w:name="Haettenschweiler"><w:panose1 w:val="020B0706040902060204"/><w:charset w:val="00"/><w:family w:val="swiss"/><w:pitch w:val="variable"/><w:sig w:usb0="00000287" w:usb1="00000000" w:usb2="00000000" w:usb3="00000000" w:csb0="0000009F" w:csb1="00000000"/><w:embedRegular r:id="rId9" w:subsetted="1" w:fontKey="{A2461C62-1657-42C0-AD49-9A9EC2B50E08}"/></w:font><w:font w:name="Segoe UI Light"><w:panose1 w:val="020B0502040204020203"/><w:charset w:val="00"/><w:family w:val="swiss"/><w:pitch w:val="variable"/><w:sig w:usb0="E4002EFF" w:usb1="C000E47F" w:usb2="00000009" w:usb3="00000000" w:csb0="000001FF" w:csb1="00000000"/><w:embedRegular r:id="rId10" w:subsetted="1" w:fontKey="{8F36B067-4886-4937-94F7-20B1B839E412}"/></w:font><w:font w:name="Avenir Next LT Pro"><w:charset w:val="00"/><w:family w:val="swiss"/><w:pitch w:val="variable"/><w:sig w:usb0="800000EF" w:usb1="5000204A" w:usb2="00000000" w:usb3="00000000" w:csb0="00000093" w:csb1="00000000"/><w:embedRegular r:id="rId11" w:subsetted="1" w:fontKey="{6001EE9D-D9E1-4CDE-81CA-BCE15A36DF39}"/></w:font><w:font w:name="Century Schoolbook"><w:panose1 w:val="02040604050505020304"/><w:charset w:val="00"/><w:family w:val="roman"/><w:pitch w:val="variable"/><w:sig w:usb0="00000287" w:usb1="00000000" w:usb2="00000000" w:usb3="00000000" w:csb0="0000009F" w:csb1="00000000"/><w:embedRegular r:id="rId12" w:subsetted="1" w:fontKey="{A20C682B-825F-4ECD-80BA-72560F0651E0}"/></w:font><w:font w:name="Bodoni MT"><w:panose1 w:val="02070603080606020203"/><w:charset w:val="00"/><w:family w:val="roman"/><w:pitch w:val="variable"/><w:sig w:usb0="00000003" w:usb1="00000000" w:usb2="00000000" w:usb3="00000000" w:csb0="00000001" w:csb1="00000000"/><w:embedRegular r:id="rId13" w:subsetted="1" w:fontKey="{767821A1-619D-4B8A-8819-4288D050321F}"/></w:font><w:font w:name="Eras Bold ITC"><w:panose1 w:val="020B0907030504020204"/><w:charset w:val="00"/><w:family w:val="swiss"/><w:pitch w:val="variable"/><w:sig w:usb0="00000003" w:usb1="00000000" w:usb2="00000000" w:usb3="00000000" w:csb0="00000001" w:csb1="00000000"/><w:embedRegular r:id="rId14" w:subsetted="1" w:fontKey="{0763CA45-071A-4A01-8EF9-1AE389AE9C43}"/></w:font><w:font w:name="Garamond"><w:panose1 w:val="02020404030301010803"/><w:charset w:val="00"/><w:family w:val="roman"/><w:pitch w:val="variable"/><w:sig w:usb0="00000287" w:usb1="00000000" w:usb2="00000000" w:usb3="00000000" w:csb0="0000009F" w:csb1="00000000"/><w:embedRegular r:id="rId15" w:subsetted="1" w:fontKey="{75ECC4DD-C156-4D3A-8C98-0789F6B0C18F}"/></w:font><w:font w:name="Impact"><w:panose1 w:val="020B0806030902050204"/><w:charset w:val="00"/><w:family w:val="swiss"/><w:pitch w:val="variable"/><w:sig w:usb0="00000287" w:usb1="00000000" w:usb2="00000000" w:usb3="00000000" w:csb0="0000009F" w:csb1="00000000"/><w:embedRegular r:id="rId16" w:subsetted="1" w:fontKey="{C427D79E-C699-4A55-9EFC-C0940EDFF62E}"/></w:font><w:font w:name="Leelawadee UI Semilight"><w:panose1 w:val="020B0402040204020203"/><w:charset w:val="00"/><w:family w:val="swiss"/><w:pitch w:val="variable"/><w:sig w:usb0="A3000003" w:usb1="00000000" w:usb2="00010000" w:usb3="00000000" w:csb0="00010101" w:csb1="00000000"/><w:embedRegular r:id="rId17" w:subsetted="1" w:fontKey="{DDA96E74-19FE-48D6-A5D6-0A2A174CDB98}"/></w:font><w:font w:name="Monotype Corsiva"><w:panose1 w:val="03010101010201010101"/><w:charset w:val="00"/><w:family w:val="script"/><w:pitch w:val="variable"/><w:sig w:usb0="00000287" w:usb1="00000000" w:usb2="00000000" w:usb3="00000000" w:csb0="0000009F" w:csb1="00000000"/><w:embedRegular r:id="rId18" w:subsetted="1" w:fontKey="{CD997C81-2A7B-4667-9173-D12AA9EB8D13}"/></w:font><w:font w:name="SimSun"><w:altName w:val="宋体"/><w:panose1 w:val="02010600030101010101"/><w:charset w:val="86"/><w:family w:val="auto"/><w:pitch w:val="variable"/><w:sig w:usb0="00000003" w:usb1="288F0000" w:usb2="00000016" w:usb3="00000000" w:csb0="00040001" w:csb1="00000000"/><w:embedRegular r:id="rId19" w:subsetted="1" w:fontKey="{919B8BE7-2853-4D06-9E72-4357F8534C08}"/></w:font><w:font w:name="Calibri Light"><w:panose1 w:val="020F0302020204030204"/><w:charset w:val="00"/><w:family w:val="swiss"/><w:pitch w:val="variable"/><w:sig w:usb0="A00002EF" w:usb1="4000207B" w:usb2="00000000" w:usb3="00000000" w:csb0="0000009F" w:csb1="00000000"/></w:font></w:fonts>